cit_fl_participation/__init__.py
cit_fl_participation/config/__init__.py
cit_fl_participation/config/schema.py
cit_fl_participation/coordinator_interface/__init__.py
cit_fl_participation/coordinator_interface/coordinator_pb2.py
cit_fl_participation/coordinator_interface/coordinator_pb2_grpc.py
cit_fl_participation/participation/__init__.py
cit_fl_participation/participation/connector.py
cit_fl_participation/participation/connector_grpc.py
cit_fl_participation/participation/participate.py
cit_fl_participation/participation/store.py
cit_fl_participation/participation/training.py
cit_fl_participation/serialization/__init__.py
cit_fl_participation/serialization/vector_serialization.py
cit_fl_participation/serialization/vector/__init__.py
cit_fl_participation/serialization/vector/conversion.py
cit_fl_participation/serialization/vector/vector_pb2.py
cit_fl_participation-0.0.9.dist-info/LICENSE
cit_fl_participation-0.0.9.dist-info/METADATA
cit_fl_participation-0.0.9.dist-info/WHEEL
cit_fl_participation-0.0.9.dist-info/top_level.txt
cit_fl_participation-0.0.9.dist-info/RECORD
