Metadata-Version: 2.1
Name: cit-fl-participation
Version: 0.0.9
Summary: A package for federated machine learning
Home-page: https://github.com/pypa/sampleproject
Author: Example Author
Author-email: info@consider-it.de
License: UNKNOWN
Project-URL: Bug Tracker, https://github.com/pypa/sampleproject/issues
Platform: UNKNOWN
Classifier: Programming Language :: Python :: 3
Classifier: License :: OSI Approved :: MIT License
Classifier: Operating System :: OS Independent
Requires-Python: >=3.6
Requires-Dist: boto3
Requires-Dist: grpcio
Requires-Dist: idna
Requires-Dist: numpy
Requires-Dist: protobuf
Requires-Dist: schema
Requires-Dist: scipy
Requires-Dist: toml
